parlant/contrib/pipecat/__init__.py
parlant/contrib/pipecat/assets/typing.wav
parlant/contrib/pipecat/parlant_service.py
parlant_pipecat-0.1.1.dist-info/METADATA
parlant_pipecat-0.1.1.dist-info/WHEEL
parlant_pipecat-0.1.1.dist-info/licenses/LICENSE
parlant_pipecat-0.1.1.dist-info/RECORD
