Metadata-Version: 2.4
Name: parlant-pipecat
Version: 0.1.1
Summary: 
License-File: LICENSE
Author: Yam Marcovitz
Author-email: yam@emcie.co
Requires-Python: >=3.10,<4.0
Classifier: Programming Language :: Python :: 3
Classifier: Programming Language :: Python :: 3.10
Classifier: Programming Language :: Python :: 3.11
Classifier: Programming Language :: Python :: 3.12
Classifier: Programming Language :: Python :: 3.13
Classifier: Programming Language :: Python :: 3.14
Requires-Dist: parlant-client (>=3.0,<4.0)
Requires-Dist: pipecat-ai[soundfile] (>=0.0,<0.1)
Requires-Dist: soundfile (>=0.13,<0.14)
